HipoMap/Scoring.py
HipoMap/__init__.py
HipoMap/classify.py
HipoMap/core.py
HipoMap/hipoClassify.py
HipoMap/hipoMap.py
HipoMap/model_rep.py
HipoMap/probmap.py
HipoMap/scoring.py
HipoMap/utils.py
hipo_map/Hipomap.py
hipo_map/__init__.py
hipo_map/hipoClassify.py
hipo_map/model_rep.py
hipo_map/WSI_Preprocessing/Preprocessing/Annotation_parsing.py
hipo_map/WSI_Preprocessing/Preprocessing/Denoising.py
hipo_map/WSI_Preprocessing/Preprocessing/Extarctingpatches.py
hipo_map/WSI_Preprocessing/Preprocessing/Localization.py
hipo_map/WSI_Preprocessing/Preprocessing/Patch.py
hipo_map/WSI_Preprocessing/Preprocessing/Patch_extraction_creatia.py
hipo_map/WSI_Preprocessing/Preprocessing/Utilities.py
hipo_map/WSI_Preprocessing/Preprocessing/WSI_Scanning.py
hipomap/Hipomap.py
hipomap/__init__.py
hipomap/core.py
hipomap/hipoClassify.py
hipomap/model_rep.py
hipomap/probmap.py
hipomap/scoring.py
hipomap/utils.py
hipomap-1.0.2.dist-info/LICENSE
hipomap-1.0.2.dist-info/METADATA
hipomap-1.0.2.dist-info/WHEEL
hipomap-1.0.2.dist-info/top_level.txt
hipomap-1.0.2.dist-info/RECORD
