Metadata-Version: 2.1
Name: hipomap
Version: 1.0.2
Summary: Histopathological image analysis using Grad-CAM representation map
Home-page: https://github.com/datax-lab/HipoMap
Author: Jeongyeon Park
Author-email: ParkJYeon2808@gmail.com
License: UNKNOWN
Platform: UNKNOWN
Classifier: Programming Language :: Python :: 3
Classifier: License :: OSI Approved :: GNU General Public License v3 or later (GPLv3+)
Classifier: Operating System :: OS Independent
Requires-Python: >=3
Requires-Dist: numpy
Requires-Dist: opencv-python
Requires-Dist: pandas
Requires-Dist: Pillow
Requires-Dist: scikit-learn
Requires-Dist: scipy
Requires-Dist: seaborn
Requires-Dist: tensorflow
Requires-Dist: matplotlib
Requires-Dist: openslide-python
